haidarlibs
