Metadata-Version: 2.1
Name: haidarlibs
Version: 0.0.15
Summary: A Secure and Powerful Python-Pyrogram Based Library For Haidar-Pyro.
Home-page: https://github.com/XhaidarX/Haidarlibs
Author: Haidar
Author-email: cosmospanas70@gmail.com
License: GNU AFFERO GENERAL PUBLIC LICENSE (v3)
Project-URL: Bug Tracker, https://github.com/XhaidarX/Haidarlibs/issues
Project-URL: Documentation, https://t.me/kynansupport
Project-URL: Source Code, https://github.com/XhaidarX/Haidarlibs
Classifier: Programming Language :: Python :: 3
Classifier: Programming Language :: Python :: 3.8
Classifier: Programming Language :: Python :: 3.9
Classifier: Programming Language :: Python :: 3.10
Classifier: Programming Language :: Python :: 3.11
Classifier: Programming Language :: Python :: 3.12
Classifier: License :: OSI Approved :: GNU General Public License v3 (GPLv3)
Classifier: Operating System :: OS Independent
Requires-Python: >3.7, <3.12
License-File: LICENSE
